dsbox_corex/__init__.py
dsbox_corex/_config.py
dsbox_corex/corex_continuous.py
dsbox_corex/corex_text.py
dsbox_corex/echo_ib.py
dsbox_corex/echo_regressor.py
dsbox_corex/corexcontinuous/__init__.py
dsbox_corex/corexcontinuous/corex_continuous.py
dsbox_corex/corexcontinuous/setup.py
dsbox_corex/corexcontinuous/linearcorex/__init__.py
dsbox_corex/corexcontinuous/linearcorex/vis_corex.py
dsbox_corex/corexcontinuous/linearcorex/linearcorex/__init__.py
dsbox_corex/corexcontinuous/linearcorex/linearcorex/linearcorex.py
dsbox_corex/corexsae/__init__.py
dsbox_corex/corexsae/corex_sae.py
dsbox_corex/corexsae/echo.py
dsbox_corex/corextext/__init__.py
dsbox_corex/corextext/corex_topic.py
dsbox_corex/echo_regression/__init__.py
dsbox_corex/echo_regression/echo_regression.py
dsbox_corex/echo_regression/setup.py
dsbox_corex/linearcorex/__init__.py
dsbox_corex/linearcorex/vis_corex.py
dsbox_corex/linearcorex/linearcorex/__init__.py
dsbox_corex/linearcorex/linearcorex/linearcorex.py
dsbox_corex-1.2.0.dist-info/LICENSE
dsbox_corex-1.2.0.dist-info/METADATA
dsbox_corex-1.2.0.dist-info/WHEEL
dsbox_corex-1.2.0.dist-info/entry_points.txt
dsbox_corex-1.2.0.dist-info/top_level.txt
dsbox_corex-1.2.0.dist-info/RECORD
